{
    "assets": {
        "gameOverBackground": {
            "path": "assets/crystal_heads_1024_768.jpg",
            "coordinates": {
                "xPos": 0,
                "yPos": 0
            }
        },
        "none": {
            "path": "nullptr",
            "coordinates": {
                "xPos": 0,
                "yPos": 0
            }
        }
    },
    "buttons": {
        "Neu": {
            "width": 150,
            "height": 50,
            "xpos": 0,
            "ypos": 125,
            "angle": 0,
            "red": 0,
            "green": 85,
            "blue": 170,
            "alpha": 255,
            "functionPointer": "restartPlay"
        },
        "Back": {
            "width": 150,
            "height": 50,
            "xpos": 0,
            "ypos": 200,
            "angle": 0,
            "red": 0,
            "green": 85,
            "blue": 170,
            "alpha": 255,
            "functionPointer": "gameOverToMain"
        }
    },
    "color": {
        "white": {
            "red": 255,
            "green": 255,
            "blue": 255,
            "alpha": 255
        }
    },
    "music": {
        "background": {
            "path": "music/Beethoven_Moonlight_Sonata_Instrumental.mp3"
        }
    },
    "sound": {
    },
    "texttexture": {
        "Over": {
            "ttf": "oxyReg30",
            "text": "He's dead, Jim!",
            "color": "white"
        },
        "Neu": {
            "ttf": "oxyReg30",
            "text": "Neu",
            "color": "white"
        },
        "Back": {
            "ttf": "oxyReg30",
            "text": "Back",
            "color": "white"
        }
    },
    "ttf": {
        "oxyReg30": {
            "path": "ttf/OxygenRegular.ttf",
            "size": 30
        }
    },
    "viewports": {
        "menu": {
            "xPos": 0,
            "yPos": 0,
            "width": 170,
            "height": 0,
            "texture": "none"
        },
        "screen": {
            "xPos": 170,
            "yPos": 0,
            "width": 470,
            "height": 0,
            "texture": "gameOverBackground"
        }
    }
}
